{
  "metadata": [
    {
      "src": [
        {
          "files": [
            "Picturepark.SDK.V1/**/*.cs"
          ],
          "exclude": [
            "**/bin/**",
            "**/obj/**"
          ],
          "cwd": "../../src"
        }
      ],
      "dest": "obj/api"
    }
  ],
  "build": {
    "content": [
      {
        "files": [
          "**/*.yml"
        ],
        "cwd": "obj/api",
        "dest": "api"
      },
      {
        "files": [
          "index.md",
          "toc.yml"
        ]
      }
    ],
    "globalMetadata": {
      "_appTitle": "Picturepark.SDK.V1 API",
      "_enableSearch": true
    },
    "dest": "api"
  }
}